config_encryptor/__init__.py
config_encryptor/encryption.py
config_encryptor/key_manager.py
config_encryptor-1.2.1.dist-info/LICENSE
config_encryptor-1.2.1.dist-info/METADATA
config_encryptor-1.2.1.dist-info/WHEEL
config_encryptor-1.2.1.dist-info/top_level.txt
config_encryptor-1.2.1.dist-info/RECORD
