Metadata-Version: 2.1
Name: config_encryptor
Version: 1.2.1
Summary: A Python package for encrypting and decrypting config files using Fernet encryption.
Home-page: https://github.com/shabir/configencrypt
Author: Shabir Ahmad
Author-email: shabir@caimi.co.kr
Classifier: Programming Language :: Python :: 3
Classifier: License :: OSI Approved :: MIT License
Classifier: Operating System :: OS Independent
Requires-Python: >=3.6
License-File: LICENSE
Requires-Dist: cryptography>=3.4.7
